{"nodes": [{"id": "docs_02_tech_stack", "label": "Tech Stack & Arsitektur", "file_type": "document", "source_file": "docs/02-tech-stack.md"}, {"id": "ar_technology", "label": "WebAR Technology", "file_type": "concept", "source_file": "docs/02-tech-stack.md"}, {"id": "rag_tutor_ai", "label": "RAG & Tutor AI", "file_type": "concept", "source_file": "docs/02-tech-stack.md"}], "edges": [], "hyperedges": [{"id": "ar_implementation_flow", "label": "AR Implementation Flow", "nodes": ["ar_codingar", "ar_arcard_samiloto_png", "public_ar_readme", "ar_technology"], "relation": "participate_in", "confidence": "INFERRED", "confidence_score": 0.85, "source_file": "docs/02-tech-stack.md"}]}